dothub/__init__.py
dothub/__main__.py
dothub/_version.py
dothub/cli.py
dothub/config.py
dothub/dict_diff.py
dothub/github_helper.py
dothub/organization.py
dothub/repository.py
dothub/utils.py
dothub-0.16.4.dist-info/DESCRIPTION.rst
dothub-0.16.4.dist-info/METADATA
dothub-0.16.4.dist-info/RECORD
dothub-0.16.4.dist-info/WHEEL
dothub-0.16.4.dist-info/entry_points.txt
dothub-0.16.4.dist-info/metadata.json
dothub-0.16.4.dist-info/top_level.txt
